{"version":1,"resource":"file:///home/dodecaneser/HTB/labs/BackDoor/scripts/cmdlinev2.py","entries":[{"id":"CHcR.py","timestamp":1655884601120},{"id":"d49u.py","timestamp":1655884837750},{"id":"v5YS.py","timestamp":1655884904240},{"id":"3mHM.py","timestamp":1655885285770},{"id":"2UrX.py","timestamp":1655885515473},{"id":"7Nad.py","timestamp":1655885631113},{"id":"66QG.py","timestamp":1655885673363},{"id":"cb6P.py","timestamp":1655886164804},{"id":"3O1H.py","timestamp":1655886203307},{"id":"Gxwm.py","timestamp":1655886299710},{"id":"4cHT.py","timestamp":1655886392027},{"id":"sAmj.py","timestamp":1655886805580},{"id":"mjC8.py","timestamp":1655886955957},{"id":"joq8.py","timestamp":1655887048614},{"id":"RNkr.py","timestamp":1655887110584},{"id":"a1St.py","timestamp":1655887290197}]}